mmrbipy/__init__.py
mmrbipy/model.py
mmrbipy-1.1.2.dist-info/LICENSE
mmrbipy-1.1.2.dist-info/METADATA
mmrbipy-1.1.2.dist-info/WHEEL
mmrbipy-1.1.2.dist-info/top_level.txt
mmrbipy-1.1.2.dist-info/RECORD
