Metadata-Version: 2.1
Name: mmrbipy
Version: 1.1.2
Summary: mmrbipy: A solver for the min-max regret binary integer programming problem (MMR-BIP)
Home-page: https://github.com/ebeleta/iDS
Author: Wei Wu
Author-email: goi@shizuoka.ac.jp
Maintainer: Wei Wu
Maintainer-email: goi@shizuoka.ac.jp
License: MIT
Platform: UNKNOWN
Classifier: Intended Audience :: Science/Research
Classifier: License :: OSI Approved :: MIT License
Classifier: Operating System :: OS Independent
Classifier: Topic :: Scientific/Engineering
Classifier: Topic :: Scientific/Engineering :: Mathematics
Classifier: Topic :: Multimedia :: Graphics
Requires-Python: >=3.6
License-File: LICENSE
Requires-Dist: gurobipy
